Workbook

Sheet Executive Summary
A1: Nursery FP&A Analytics — Executive Summary
A2: Portfolio case study using public blueberry market data as external drivers and transparent modeled financial assumptions.
A4: Forecast Revenue | D4: Revenue vs Budget | G4: Forecast EBITDA | J4: EBITDA vs Budget
A5: ='Budget vs Forecast'!C9 -> 4194679.7 | D5: ='Budget vs Forecast'!E9 -> 0.029559108 | G5: ='Budget vs Forecast'!G9 -> 1188822.8 | J5: ='Budget vs Forecast'!I9 -> 0.067436212
A8: Forecast Gross Margin | D8: Forecast EBITDA Margin
A9: =SUMIFS('Raw_Monthly'!$K$4:$K$147,'Raw_Monthly'!$F$4:$F$147,"Forecast",'Raw_Monthly'!$B$4:$B$147,2025)/SUMIFS('Raw_Monthly'!$I$4:$I$147,'Raw_Monthly'!$F$4:$F$147,"Forecast",'Raw_Monthly'!$B$4:$B$147,2025) -> 0.58093178 | D9: =SUMIFS('Raw_Monthly'!$N$4:$N$147,'Raw_Monthly'!$F$4:$F$147,"Forecast",'Raw_Monthly'!$B$4:$B$147,2025)/SUMIFS('Raw_Monthly'!$I$4:$I$147,'Raw_Monthly'!$F$4:$F$147,"Forecast",'Raw_Monthly'!$B$4:$B$147,2025) -> 0.28341205
A12: 2025 forecast revenue is +3.0% vs budget and EBITDA is +6.7% vs budget. Peru is the strongest regional revenue performer (+9.1% vs budget), while Chile is the main downside (-6.9%). Management focus: protect margin in weaker regions, validate the Peru growth assumptions, and use the CAPEX sensitivity analysis before committing expansion capital.
A17: Regional Snapshot
A18: Country | B18: Revenue Var (%) | C18: EBITDA Var (%) | D18: Status
A19: Chile | B19: ='Budget vs Forecast'!E5 -> -0.069399801 | C19: ='Budget vs Forecast'!I5 -> -0.15575446 | D19: =IF(B19>=0,"Ahead","Below") -> Below
A20: Mexico | B20: ='Budget vs Forecast'!E6 -> 0.025097658 | C20: ='Budget vs Forecast'!I6 -> 0.058458343 | D20: =IF(B20>=0,"Ahead","Below") -> Ahead
A21: Peru | B21: ='Budget vs Forecast'!E7 -> 0.090800996 | C21: ='Budget vs Forecast'!I7 -> 0.21803169 | D21: =IF(B21>=0,"Ahead","Below") -> Ahead
A22: Spain | B22: ='Budget vs Forecast'!E8 -> -0.034849748 | C22: ='Budget vs Forecast'!I8 -> -0.078076032 | D22: =IF(B22>=0,"Ahead","Below") -> Below

Sheet Monthly Performance
A1: 2025 Monthly Performance
A2: Monthly Budget vs Forecast reporting using the modeled regional seasonality assumptions.
A4: Month | B4: Budget Revenue ($) | C4: Forecast Revenue ($) | D4: Revenue Var (%) | E4: Budget EBITDA ($) | F4: Forecast EBITDA ($) | G4: EBITDA Var (%)
A5: Jan | B5: =SUMIFS('Raw_Monthly'!$I$4:$I$147,'Raw_Monthly'!$C$4:$C$147,1,'Raw_Monthly'!$F$4:$F$147,"Budget",'Raw_Monthly'!$B$4:$B$147,2025) -> 229990.78 | C5: =SUMIFS('Raw_Monthly'!$I$4:$I$147,'Raw_Monthly'!$C$4:$C$147,1,'Raw_Monthly'!$F$4:$F$147,"Forecast",'Raw_Monthly'!$B$4:$B$147,2025) -> 235510.27 | D5: =IFERROR(C5/B5-1,0) -> 0.023998725 | E5: =SUMIFS('Raw_Monthly'!$N$4:$N$147,'Raw_Monthly'!$C$4:$C$147,1,'Raw_Monthly'!$F$4:$F$147,"Budget",'Raw_Monthly'!$B$4:$B$147,2025) -> 29398.601 | F5: =SUMIFS('Raw_Monthly'!$N$4:$N$147,'Raw_Monthly'!$C$4:$C$147,1,'Raw_Monthly'!$F$4:$F$147,"Forecast",'Raw_Monthly'!$B$4:$B$147,2025) -> 32841.381 | G5: =IFERROR(F5/E5-1,0) -> 0.11710691
A6: Feb | B6: =SUMIFS('Raw_Monthly'!$I$4:$I$147,'Raw_Monthly'!$C$4:$C$147,2,'Raw_Monthly'!$F$4:$F$147,"Budget",'Raw_Monthly'!$B$4:$B$147,2025) -> 270733.27 | C6: =SUMIFS('Raw_Monthly'!$I$4:$I$147,'Raw_Monthly'!$C$4:$C$147,2,'Raw_Monthly'!$F$4:$F$147,"Forecast",'Raw_Monthly'!$B$4:$B$147,2025) -> 277457.06 | D6: =IFERROR(C6/B6-1,0) -> 0.024835504 | E6: =SUMIFS('Raw_Monthly'!$N$4:$N$147,'Raw_Monthly'!$C$4:$C$147,2,'Raw_Monthly'!$F$4:$F$147,"Budget",'Raw_Monthly'!$B$4:$B$147,2025) -> 53015.78 | F6: =SUMIFS('Raw_Monthly'!$N$4:$N$147,'Raw_Monthly'!$C$4:$C$147,2,'Raw_Monthly'!$F$4:$F$147,"Forecast",'Raw_Monthly'!$B$4:$B$147,2025) -> 57209.608 | G6: =IFERROR(F6/E6-1,0) -> 0.079105287
A7: Mar | B7: =SUMIFS('Raw_Monthly'!$I$4:$I$147,'Raw_Monthly'!$C$4:$C$147,3,'Raw_Monthly'!$F$4:$F$147,"Budget",'Raw_Monthly'!$B$4:$B$147,2025) -> 331321.7 | C7: =SUMIFS('Raw_Monthly'!$I$4:$I$147,'Raw_Monthly'!$C$4:$C$147,3,'Raw_Monthly'!$F$4:$F$147,"Forecast",'Raw_Monthly'!$B$4:$B$147,2025) -> 338254.72 | D7: =IFERROR(C7/B7-1,0) -> 0.020925324 | E7: =SUMIFS('Raw_Monthly'!$N$4:$N$147,'Raw_Monthly'!$C$4:$C$147,3,'Raw_Monthly'!$F$4:$F$147,"Budget",'Raw_Monthly'!$B$4:$B$147,2025) -> 88245.048 | F7: =SUMIFS('Raw_Monthly'!$N$4:$N$147,'Raw_Monthly'!$C$4:$C$147,3,'Raw_Monthly'!$F$4:$F$147,"Forecast",'Raw_Monthly'!$B$4:$B$147,2025) -> 92552.606 | G7: =IFERROR(F7/E7-1,0) -> 0.048813592
A8: Apr | B8: =SUMIFS('Raw_Monthly'!$I$4:$I$147,'Raw_Monthly'!$C$4:$C$147,4,'Raw_Monthly'!$F$4:$F$147,"Budget",'Raw_Monthly'!$B$4:$B$147,2025) -> 386378.89 | C8: =SUMIFS('Raw_Monthly'!$I$4:$I$147,'Raw_Monthly'!$C$4:$C$147,4,'Raw_Monthly'!$F$4:$F$147,"Forecast",'Raw_Monthly'!$B$4:$B$147,2025) -> 393713.88 | D8: =IFERROR(C8/B8-1,0) -> 0.01898394 | E8: =SUMIFS('Raw_Monthly'!$N$4:$N$147,'Raw_Monthly'!$C$4:$C$147,4,'Raw_Monthly'!$F$4:$F$147,"Budget",'Raw_Monthly'!$B$4:$B$147,2025) -> 120213.98 | F8: =SUMIFS('Raw_Monthly'!$N$4:$N$147,'Raw_Monthly'!$C$4:$C$147,4,'Raw_Monthly'!$F$4:$F$147,"Forecast",'Raw_Monthly'!$B$4:$B$147,2025) -> 124759.9 | G8: =IFERROR(F8/E8-1,0) -> 0.037815263
A9: May | B9: =SUMIFS('Raw_Monthly'!$I$4:$I$147,'Raw_Monthly'!$C$4:$C$147,5,'Raw_Monthly'!$F$4:$F$147,"Budget",'Raw_Monthly'!$B$4:$B$147,2025) -> 427121.37 | C9: =SUMIFS('Raw_Monthly'!$I$4:$I$147,'Raw_Monthly'!$C$4:$C$147,5,'Raw_Monthly'!$F$4:$F$147,"Forecast",'Raw_Monthly'!$B$4:$B$147,2025) -> 435660.68 | D9: =IFERROR(C9/B9-1,0) -> 0.01999269 | E9: =SUMIFS('Raw_Monthly'!$N$4:$N$147,'Raw_Monthly'!$C$4:$C$147,5,'Raw_Monthly'!$F$4:$F$147,"Budget",'Raw_Monthly'!$B$4:$B$147,2025) -> 143831.15 | F9: =SUMIFS('Raw_Monthly'!$N$4:$N$147,'Raw_Monthly'!$C$4:$C$147,5,'Raw_Monthly'!$F$4:$F$147,"Forecast",'Raw_Monthly'!$B$4:$B$147,2025) -> 149128.13 | G9: =IFERROR(F9/E9-1,0) -> 0.036827711
A10: Jun | B10: =SUMIFS('Raw_Monthly'!$I$4:$I$147,'Raw_Monthly'!$C$4:$C$147,6,'Raw_Monthly'!$F$4:$F$147,"Budget",'Raw_Monthly'!$B$4:$B$147,2025) -> 421739.55 | C10: =SUMIFS('Raw_Monthly'!$I$4:$I$147,'Raw_Monthly'!$C$4:$C$147,6,'Raw_Monthly'!$F$4:$F$147,"Forecast",'Raw_Monthly'!$B$4:$B$147,2025) -> 432980.34 | D10: =IFERROR(C10/B10-1,0) -> 0.026653377 | E10: =SUMIFS('Raw_Monthly'!$N$4:$N$147,'Raw_Monthly'!$C$4:$C$147,6,'Raw_Monthly'!$F$4:$F$147,"Budget",'Raw_Monthly'!$B$4:$B$147,2025) -> 140523.53 | F10: =SUMIFS('Raw_Monthly'!$N$4:$N$147,'Raw_Monthly'!$C$4:$C$147,6,'Raw_Monthly'!$F$4:$F$147,"Forecast",'Raw_Monthly'!$B$4:$B$147,2025) -> 147521.34 | G10: =IFERROR(F10/E10-1,0) -> 0.049798118
A11: Jul | B11: =SUMIFS('Raw_Monthly'!$I$4:$I$147,'Raw_Monthly'!$C$4:$C$147,7,'Raw_Monthly'!$F$4:$F$147,"Budget",'Raw_Monthly'!$B$4:$B$147,2025) -> 407574.29 | C11: =SUMIFS('Raw_Monthly'!$I$4:$I$147,'Raw_Monthly'!$C$4:$C$147,7,'Raw_Monthly'!$F$4:$F$147,"Forecast",'Raw_Monthly'!$B$4:$B$147,2025) -> 422126.12 | D11: =IFERROR(C11/B11-1,0) -> 0.035703506 | E11: =SUMIFS('Raw_Monthly'!$N$4:$N$147,'Raw_Monthly'!$C$4:$C$147,7,'Raw_Monthly'!$F$4:$F$147,"Budget",'Raw_Monthly'!$B$4:$B$147,2025) -> 132124.51 | F11: =SUMIFS('Raw_Monthly'!$N$4:$N$147,'Raw_Monthly'!$C$4:$C$147,7,'Raw_Monthly'!$F$4:$F$147,"Forecast",'Raw_Monthly'!$B$4:$B$147,2025) -> 141211.2 | G11: =IFERROR(F11/E11-1,0) -> 0.068773696
A12: Aug | B12: =SUMIFS('Raw_Monthly'!$I$4:$I$147,'Raw_Monthly'!$C$4:$C$147,8,'Raw_Monthly'!$F$4:$F$147,"Budget",'Raw_Monthly'!$B$4:$B$147,2025) -> 381746.51 | C12: =SUMIFS('Raw_Monthly'!$I$4:$I$147,'Raw_Monthly'!$C$4:$C$147,8,'Raw_Monthly'!$F$4:$F$147,"Forecast",'Raw_Monthly'!$B$4:$B$147,2025) -> 397143.31 | D12: =IFERROR(C12/B12-1,0) -> 0.040332513 | E12: =SUMIFS('Raw_Monthly'!$N$4:$N$147,'Raw_Monthly'!$C$4:$C$147,8,'Raw_Monthly'!$F$4:$F$147,"Budget",'Raw_Monthly'!$B$4:$B$147,2025) -> 117031.94 | F12: =SUMIFS('Raw_Monthly'!$N$4:$N$147,'Raw_Monthly'!$C$4:$C$147,8,'Raw_Monthly'!$F$4:$F$147,"Forecast",'Raw_Monthly'!$B$4:$B$147,2025) -> 126655.84 | G12: =IFERROR(F12/E12-1,0) -> 0.082233123
A13: Sep | B13: =SUMIFS('Raw_Monthly'!$I$4:$I$147,'Raw_Monthly'!$C$4:$C$147,9,'Raw_Monthly'!$F$4:$F$147,"Budget",'Raw_Monthly'!$B$4:$B$147,2025) -> 341004.03 | C13: =SUMIFS('Raw_Monthly'!$I$4:$I$147,'Raw_Monthly'!$C$4:$C$147,9,'Raw_Monthly'!$F$4:$F$147,"Forecast",'Raw_Monthly'!$B$4:$B$147,2025) -> 355196.51 | D13: =IFERROR(C13/B13-1,0) -> 0.041619698 | E13: =SUMIFS('Raw_Monthly'!$N$4:$N$147,'Raw_Monthly'!$C$4:$C$147,9,'Raw_Monthly'!$F$4:$F$147,"Budget",'Raw_Monthly'!$B$4:$B$147,2025) -> 93414.757 | F13: =SUMIFS('Raw_Monthly'!$N$4:$N$147,'Raw_Monthly'!$C$4:$C$147,9,'Raw_Monthly'!$F$4:$F$147,"Forecast",'Raw_Monthly'!$B$4:$B$147,2025) -> 102287.61 | G13: =IFERROR(F13/E13-1,0) -> 0.094983413
A14: Oct | B14: =SUMIFS('Raw_Monthly'!$I$4:$I$147,'Raw_Monthly'!$C$4:$C$147,10,'Raw_Monthly'!$F$4:$F$147,"Budget",'Raw_Monthly'!$B$4:$B$147,2025) -> 320558.07 | C14: =SUMIFS('Raw_Monthly'!$I$4:$I$147,'Raw_Monthly'!$C$4:$C$147,10,'Raw_Monthly'!$F$4:$F$147,"Forecast",'Raw_Monthly'!$B$4:$B$147,2025) -> 332894.04 | D14: =IFERROR(C14/B14-1,0) -> 0.038482797 | E14: =SUMIFS('Raw_Monthly'!$N$4:$N$147,'Raw_Monthly'!$C$4:$C$147,10,'Raw_Monthly'!$F$4:$F$147,"Budget",'Raw_Monthly'!$B$4:$B$147,2025) -> 81629.807 | F14: =SUMIFS('Raw_Monthly'!$N$4:$N$147,'Raw_Monthly'!$C$4:$C$147,10,'Raw_Monthly'!$F$4:$F$147,"Forecast",'Raw_Monthly'!$B$4:$B$147,2025) -> 89339.036 | G14: =IFERROR(F14/E14-1,0) -> 0.094441339
A15: Nov | B15: =SUMIFS('Raw_Monthly'!$I$4:$I$147,'Raw_Monthly'!$C$4:$C$147,11,'Raw_Monthly'!$F$4:$F$147,"Budget",'Raw_Monthly'!$B$4:$B$147,2025) -> 305643.36 | C15: =SUMIFS('Raw_Monthly'!$I$4:$I$147,'Raw_Monthly'!$C$4:$C$147,11,'Raw_Monthly'!$F$4:$F$147,"Forecast",'Raw_Monthly'!$B$4:$B$147,2025) -> 315930.06 | D15: =IFERROR(C15/B15-1,0) -> 0.033655874 | E15: =SUMIFS('Raw_Monthly'!$N$4:$N$147,'Raw_Monthly'!$C$4:$C$147,11,'Raw_Monthly'!$F$4:$F$147,"Budget",'Raw_Monthly'!$B$4:$B$147,2025) -> 73105.199 | F15: =SUMIFS('Raw_Monthly'!$N$4:$N$147,'Raw_Monthly'!$C$4:$C$147,11,'Raw_Monthly'!$F$4:$F$147,"Forecast",'Raw_Monthly'!$B$4:$B$147,2025) -> 79526.167 | G15: =IFERROR(F15/E15-1,0) -> 0.087831894
A16: Dec | B16: =SUMIFS('Raw_Monthly'!$I$4:$I$147,'Raw_Monthly'!$C$4:$C$147,12,'Raw_Monthly'!$F$4:$F$147,"Budget",'Raw_Monthly'!$B$4:$B$147,2025) -> 250436.74 | C16: =SUMIFS('Raw_Monthly'!$I$4:$I$147,'Raw_Monthly'!$C$4:$C$147,12,'Raw_Monthly'!$F$4:$F$147,"Forecast",'Raw_Monthly'!$B$4:$B$147,2025) -> 257812.74 | D16: =IFERROR(C16/B16-1,0) -> 0.029452544 | E16: =SUMIFS('Raw_Monthly'!$N$4:$N$147,'Raw_Monthly'!$C$4:$C$147,12,'Raw_Monthly'!$F$4:$F$147,"Budget",'Raw_Monthly'!$B$4:$B$147,2025) -> 41183.551 | F16: =SUMIFS('Raw_Monthly'!$N$4:$N$147,'Raw_Monthly'!$C$4:$C$147,12,'Raw_Monthly'!$F$4:$F$147,"Forecast",'Raw_Monthly'!$B$4:$B$147,2025) -> 45789.954 | G16: =IFERROR(F16/E16-1,0) -> 0.11185057
A17: Total | B17: =SUM(B5:B16) -> 4074248.6 | C17: =SUM(C5:C16) -> 4194679.7 | D17: =IFERROR(C17/B17-1,0) -> 0.029559108 | E17: =SUM(E5:E16) -> 1113717.8 | F17: =SUM(F5:F16) -> 1188822.8 | G17: =IFERROR(F17/E17-1,0) -> 0.067436212

Sheet Budget vs Forecast
A1: 2025 Budget vs Forecast
A2: Regional variance analysis. Green font indicates formulas linked to source data on another worksheet.
A4: Country | B4: Budget Revenue ($) | C4: Forecast Revenue ($) | D4: Revenue Var ($) | E4: Revenue Var (%) | F4: Budget EBITDA ($) | G4: Forecast EBITDA ($) | H4: EBITDA Var ($) | I4: EBITDA Var (%)
A5: Chile | B5: =SUMIFS('Raw_Monthly'!$I$4:$I$147,'Raw_Monthly'!$E$4:$E$147,$A5,'Raw_Monthly'!$F$4:$F$147,"Budget",'Raw_Monthly'!$B$4:$B$147,2025) -> 878344.23 | C5: =SUMIFS('Raw_Monthly'!$I$4:$I$147,'Raw_Monthly'!$E$4:$E$147,$A5,'Raw_Monthly'!$F$4:$F$147,"Forecast",'Raw_Monthly'!$B$4:$B$147,2025) -> 817387.31 | D5: =C5-B5 -> -60956.915 | E5: =IFERROR(D5/B5,0) -> -0.069399801 | F5: =SUMIFS('Raw_Monthly'!$N$4:$N$147,'Raw_Monthly'!$E$4:$E$147,$A5,'Raw_Monthly'!$F$4:$F$147,"Budget",'Raw_Monthly'!$B$4:$B$147,2025) -> 249140.73 | G5: =SUMIFS('Raw_Monthly'!$N$4:$N$147,'Raw_Monthly'!$E$4:$E$147,$A5,'Raw_Monthly'!$F$4:$F$147,"Forecast",'Raw_Monthly'!$B$4:$B$147,2025) -> 210335.95 | H5: =G5-F5 -> -38804.779 | I5: =IFERROR(H5/F5,0) -> -0.15575446
A6: Mexico | B6: =SUMIFS('Raw_Monthly'!$I$4:$I$147,'Raw_Monthly'!$E$4:$E$147,$A6,'Raw_Monthly'!$F$4:$F$147,"Budget",'Raw_Monthly'!$B$4:$B$147,2025) -> 598182.82 | C6: =SUMIFS('Raw_Monthly'!$I$4:$I$147,'Raw_Monthly'!$E$4:$E$147,$A6,'Raw_Monthly'!$F$4:$F$147,"Forecast",'Raw_Monthly'!$B$4:$B$147,2025) -> 613195.81 | D6: =C6-B6 -> 15012.988 | E6: =IFERROR(D6/B6,0) -> 0.025097658 | F6: =SUMIFS('Raw_Monthly'!$N$4:$N$147,'Raw_Monthly'!$E$4:$E$147,$A6,'Raw_Monthly'!$F$4:$F$147,"Budget",'Raw_Monthly'!$B$4:$B$147,2025) -> 171248 | G6: =SUMIFS('Raw_Monthly'!$N$4:$N$147,'Raw_Monthly'!$E$4:$E$147,$A6,'Raw_Monthly'!$F$4:$F$147,"Forecast",'Raw_Monthly'!$B$4:$B$147,2025) -> 181258.87 | H6: =G6-F6 -> 10010.874 | I6: =IFERROR(H6/F6,0) -> 0.058458343
A7: Peru | B7: =SUMIFS('Raw_Monthly'!$I$4:$I$147,'Raw_Monthly'!$E$4:$E$147,$A7,'Raw_Monthly'!$F$4:$F$147,"Budget",'Raw_Monthly'!$B$4:$B$147,2025) -> 2044596.1 | C7: =SUMIFS('Raw_Monthly'!$I$4:$I$147,'Raw_Monthly'!$E$4:$E$147,$A7,'Raw_Monthly'!$F$4:$F$147,"Forecast",'Raw_Monthly'!$B$4:$B$147,2025) -> 2230247.5 | D7: =C7-B7 -> 185651.36 | E7: =IFERROR(D7/B7,0) -> 0.090800996 | F7: =SUMIFS('Raw_Monthly'!$N$4:$N$147,'Raw_Monthly'!$E$4:$E$147,$A7,'Raw_Monthly'!$F$4:$F$147,"Budget",'Raw_Monthly'!$B$4:$B$147,2025) -> 533694.97 | G7: =SUMIFS('Raw_Monthly'!$N$4:$N$147,'Raw_Monthly'!$E$4:$E$147,$A7,'Raw_Monthly'!$F$4:$F$147,"Forecast",'Raw_Monthly'!$B$4:$B$147,2025) -> 650057.39 | H7: =G7-F7 -> 116362.42 | I7: =IFERROR(H7/F7,0) -> 0.21803169
A8: Spain | B8: =SUMIFS('Raw_Monthly'!$I$4:$I$147,'Raw_Monthly'!$E$4:$E$147,$A8,'Raw_Monthly'!$F$4:$F$147,"Budget",'Raw_Monthly'!$B$4:$B$147,2025) -> 553125.41 | C8: =SUMIFS('Raw_Monthly'!$I$4:$I$147,'Raw_Monthly'!$E$4:$E$147,$A8,'Raw_Monthly'!$F$4:$F$147,"Forecast",'Raw_Monthly'!$B$4:$B$147,2025) -> 533849.13 | D8: =C8-B8 -> -19276.281 | E8: =IFERROR(D8/B8,0) -> -0.034849748 | F8: =SUMIFS('Raw_Monthly'!$N$4:$N$147,'Raw_Monthly'!$E$4:$E$147,$A8,'Raw_Monthly'!$F$4:$F$147,"Budget",'Raw_Monthly'!$B$4:$B$147,2025) -> 159634.15 | G8: =SUMIFS('Raw_Monthly'!$N$4:$N$147,'Raw_Monthly'!$E$4:$E$147,$A8,'Raw_Monthly'!$F$4:$F$147,"Forecast",'Raw_Monthly'!$B$4:$B$147,2025) -> 147170.55 | H8: =G8-F8 -> -12463.601 | I8: =IFERROR(H8/F8,0) -> -0.078076032
A9: Total | B9: =SUM(B5:B8) -> 4074248.6 | C9: =SUM(C5:C8) -> 4194679.7 | D9: =SUM(D5:D8) -> 120431.15 | E9: =IFERROR(D9/B9,0) -> 0.029559108 | F9: =SUM(F5:F8) -> 1113717.8 | G9: =SUM(G5:G8) -> 1188822.8 | H9: =SUM(H5:H8) -> 75104.913 | I9: =IFERROR(H9/F9,0) -> 0.067436212

Sheet CAPEX
A1: CAPEX Decision Support
A2: Potential Peru nursery capacity expansion. NPV and IRR are calculated from scenario cash flows in this workbook.
A4: Scenario | B4: Initial Investment ($) | C4: Discount Rate | D4: NPV ($) | E4: IRR | F4: Payback (Years)
A5: Downside | B5: =INDEX('Raw_CAPEX'!$B$4:$B$6,MATCH($A5,'Raw_CAPEX'!$A$4:$A$6,0)) -> 850000 | C5: =INDEX('Raw_CAPEX'!$C$4:$C$6,MATCH($A5,'Raw_CAPEX'!$A$4:$A$6,0))/100 -> 0.1 | D5: =INDEX('Raw_CAPEX'!$D$4:$D$6,MATCH($A5,'Raw_CAPEX'!$A$4:$A$6,0)) -> -241346.25 | E5: =INDEX('Raw_CAPEX'!$E$4:$E$6,MATCH($A5,'Raw_CAPEX'!$A$4:$A$6,0))/100 -> -0.00060875331 | F5: =INDEX('Raw_CAPEX'!$F$4:$F$6,MATCH($A5,'Raw_CAPEX'!$A$4:$A$6,0)) -> None
A6: Base | B6: =INDEX('Raw_CAPEX'!$B$4:$B$6,MATCH($A6,'Raw_CAPEX'!$A$4:$A$6,0)) -> 850000 | C6: =INDEX('Raw_CAPEX'!$C$4:$C$6,MATCH($A6,'Raw_CAPEX'!$A$4:$A$6,0))/100 -> 0.1 | D6: =INDEX('Raw_CAPEX'!$D$4:$D$6,MATCH($A6,'Raw_CAPEX'!$A$4:$A$6,0)) -> 218046.07 | E6: =INDEX('Raw_CAPEX'!$E$4:$E$6,MATCH($A6,'Raw_CAPEX'!$A$4:$A$6,0))/100 -> 0.18030556 | F6: =INDEX('Raw_CAPEX'!$F$4:$F$6,MATCH($A6,'Raw_CAPEX'!$A$4:$A$6,0)) -> 3.5613413
A7: Upside | B7: =INDEX('Raw_CAPEX'!$B$4:$B$6,MATCH($A7,'Raw_CAPEX'!$A$4:$A$6,0)) -> 850000 | C7: =INDEX('Raw_CAPEX'!$C$4:$C$6,MATCH($A7,'Raw_CAPEX'!$A$4:$A$6,0))/100 -> 0.1 | D7: =INDEX('Raw_CAPEX'!$D$4:$D$6,MATCH($A7,'Raw_CAPEX'!$A$4:$A$6,0)) -> 612720.65 | E7: =INDEX('Raw_CAPEX'!$E$4:$E$6,MATCH($A7,'Raw_CAPEX'!$A$4:$A$6,0))/100 -> 0.31037742 | F7: =INDEX('Raw_CAPEX'!$F$4:$F$6,MATCH($A7,'Raw_CAPEX'!$A$4:$A$6,0)) -> 2.7932139
A9: Scenario Cash Flows and Formula Check
A10: Scenario | B10: Year 0 | C10: Year 1 | D10: Year 2 | E10: Year 3 | F10: Year 4 | G10: Year 5 | H10: NPV ($) | I10: IRR | J10: Payback (Years)
A11: Downside | B11: =SUMIFS('Raw_CAPEX'!$J$11:$J$28,'Raw_CAPEX'!$A$11:$A$28,$A11,'Raw_CAPEX'!$B$11:$B$28,0) -> -850000 | C11: =SUMIFS('Raw_CAPEX'!$J$11:$J$28,'Raw_CAPEX'!$A$11:$A$28,$A11,'Raw_CAPEX'!$B$11:$B$28,1) -> 87437.5 | D11: =SUMIFS('Raw_CAPEX'!$J$11:$J$28,'Raw_CAPEX'!$A$11:$A$28,$A11,'Raw_CAPEX'!$B$11:$B$28,2) -> 120842.5 | E11: =SUMIFS('Raw_CAPEX'!$J$11:$J$28,'Raw_CAPEX'!$A$11:$A$28,$A11,'Raw_CAPEX'!$B$11:$B$28,3) -> 154942.54 | F11: =SUMIFS('Raw_CAPEX'!$J$11:$J$28,'Raw_CAPEX'!$A$11:$A$28,$A11,'Raw_CAPEX'!$B$11:$B$28,4) -> 189730.95 | G11: =SUMIFS('Raw_CAPEX'!$J$11:$J$28,'Raw_CAPEX'!$A$11:$A$28,$A11,'Raw_CAPEX'!$B$11:$B$28,5) -> 295199.81 | H11: =NPV(INDEX($C$5:$C$7,MATCH($A11,$A$5:$A$7,0)),C11:G11)+B11 -> -241346.25 | I11: =IRR(B11:G11) -> -0.00060875331 | J11: =INDEX($F$5:$F$7,MATCH($A11,$A$5:$A$7,0)) -> None
A12: Base | B12: =SUMIFS('Raw_CAPEX'!$J$11:$J$28,'Raw_CAPEX'!$A$11:$A$28,$A12,'Raw_CAPEX'!$B$11:$B$28,0) -> -850000 | C12: =SUMIFS('Raw_CAPEX'!$J$11:$J$28,'Raw_CAPEX'!$A$11:$A$28,$A12,'Raw_CAPEX'!$B$11:$B$28,1) -> 170000 | D12: =SUMIFS('Raw_CAPEX'!$J$11:$J$28,'Raw_CAPEX'!$A$11:$A$28,$A12,'Raw_CAPEX'!$B$11:$B$28,2) -> 221500 | E12: =SUMIFS('Raw_CAPEX'!$J$11:$J$28,'Raw_CAPEX'!$A$11:$A$28,$A12,'Raw_CAPEX'!$B$11:$B$28,3) -> 274245.5 | F12: =SUMIFS('Raw_CAPEX'!$J$11:$J$28,'Raw_CAPEX'!$A$11:$A$28,$A12,'Raw_CAPEX'!$B$11:$B$28,4) -> 328239.72 | G12: =SUMIFS('Raw_CAPEX'!$J$11:$J$28,'Raw_CAPEX'!$A$11:$A$28,$A12,'Raw_CAPEX'!$B$11:$B$28,5) -> 483484.62 | H12: =NPV(INDEX($C$5:$C$7,MATCH($A12,$A$5:$A$7,0)),C12:G12)+B12 -> 218046.07 | I12: =IRR(B12:G12) -> 0.18030556 | J12: =INDEX($F$5:$F$7,MATCH($A12,$A$5:$A$7,0)) -> 3.5613413
A13: Upside | B13: =SUMIFS('Raw_CAPEX'!$J$11:$J$28,'Raw_CAPEX'!$A$11:$A$28,$A13,'Raw_CAPEX'!$B$11:$B$28,0) -> -850000 | C13: =SUMIFS('Raw_CAPEX'!$J$11:$J$28,'Raw_CAPEX'!$A$11:$A$28,$A13,'Raw_CAPEX'!$B$11:$B$28,1) -> 241600 | D13: =SUMIFS('Raw_CAPEX'!$J$11:$J$28,'Raw_CAPEX'!$A$11:$A$28,$A13,'Raw_CAPEX'!$B$11:$B$28,2) -> 308794 | E13: =SUMIFS('Raw_CAPEX'!$J$11:$J$28,'Raw_CAPEX'!$A$11:$A$28,$A13,'Raw_CAPEX'!$B$11:$B$28,3) -> 377711.51 | F13: =SUMIFS('Raw_CAPEX'!$J$11:$J$28,'Raw_CAPEX'!$A$11:$A$28,$A13,'Raw_CAPEX'!$B$11:$B$28,4) -> 448364.36 | G13: =SUMIFS('Raw_CAPEX'!$J$11:$J$28,'Raw_CAPEX'!$A$11:$A$28,$A13,'Raw_CAPEX'!$B$11:$B$28,5) -> 640763.14 | H13: =NPV(INDEX($C$5:$C$7,MATCH($A13,$A$5:$A$7,0)),C13:G13)+B13 -> 612720.65 | I13: =IRR(B13:G13) -> 0.31037742 | J13: =INDEX($F$5:$F$7,MATCH($A13,$A$5:$A$7,0)) -> 2.7932139
A15: Base case recommendation: proceed, subject to operational validation. The modeled investment produces NPV of $218,046, IRR of 18.0% versus a 10.0% discount rate, with payback in approximately 3.6 years. The downside case should be monitored because it captures demand and cost risk.

Sheet Assumptions
A1: Model Assumptions
A2: Blue font = hardcoded/model inputs. Financial company assumptions are synthetic; market drivers originate from FAOSTAT.
A4: Country | B4: Market Share | C4: Plants / ha | D4: Replacement Rate | E4: Price / Plant ($) | F4: Variable Cost / Plant ($) | G4: Annual OPEX ($) | H4: Budget Growth | I4: Forecast Adjustment
A5: Peru | B5: 0.055 | C5: 3300 | D5: 0.085 | E5: 4.1 | F5: 1.72 | G5: 620000 | H5: 0.12 | I5: 0.08
A6: Spain | B6: 0.09 | C6: 3200 | D6: 0.075 | E6: 4.55 | F6: 1.85 | G6: 160000 | H6: 0.06 | I6: -0.03
A7: Chile | B7: 0.07 | C7: 3000 | D7: 0.065 | E7: 4.3 | F7: 1.79 | G7: 250000 | H7: 0.04 | I7: -0.06
A8: Mexico | B8: 0.08 | C8: 3400 | D8: 0.08 | E8: 4.25 | F8: 1.76 | G8: 170000 | H8: 0.08 | I8: 0.02
A11: Assumption Lookup (editable)
A13: Selected Country | B13: Peru
A14: Price / Plant | B14: =INDEX($E$5:$E$8,MATCH($B$13,$A$5:$A$8,0)) -> 4.1
A15: Market Share | B15: =INDEX($B$5:$B$8,MATCH($B$13,$A$5:$A$8,0)) -> 0.055
A16: Annual OPEX | B16: =INDEX($G$5:$G$8,MATCH($B$13,$A$5:$A$8,0)) -> 620000
A19: Monthly Seasonality Assumptions
A20: Country | B20: Month_Num | C20: Month | D20: Sales_Weight
A21: Chile | B21: 1 | C21: Jan | D21: 0.06
A22: Chile | B22: 2 | C22: Feb | D22: 0.07
A23: Chile | B23: 3 | C23: Mar | D23: 0.09
A24: Chile | B24: 4 | C24: Apr | D24: 0.11
A25: Chile | B25: 5 | C25: May | D25: 0.12
A26: Chile | B26: 6 | C26: Jun | D26: 0.11
A27: Chile | B27: 7 | C27: Jul | D27: 0.09
A28: Chile | B28: 8 | C28: Aug | D28: 0.08
A29: Chile | B29: 9 | C29: Sep | D29: 0.07
A30: Chile | B30: 10 | C30: Oct | D30: 0.07
A31: Chile | B31: 11 | C31: Nov | D31: 0.07
A32: Chile | B32: 12 | C32: Dec | D32: 0.06
... A68: Spain | B68: 12 | C68: Dec | D68: 0.06

Sheet Raw_Monthly
A1: Source: FAOSTAT Production Crops and Livestock (external market drivers). Company financials and seasonality are modeled assumptions. | Z1: FAOSTAT source
A3: Date | B3: Year | C3: Month_Num | D3: Month | E3: Country | F3: Scenario | G3: Units_Sold | H3: Price_per_Plant | I3: Revenue | J3: COGS | K3: Gross_Profit | L3: Gross_Margin_pct | M3: Operating_Expenses | N3: EBITDA | O3: EBITDA_Margin_pct | P3: Market_Area_Harvested_ha | Q3: Market_Production_t | R3: Market_Yield_kg_ha | S3: Budget_Revenue | T3: Budget_EBITDA | U3: Budget_Units_Sold | V3: Revenue_Variance_vs_Budget | W3: Revenue_Variance_vs_Budget_pct | X3: EBITDA_Variance_vs_Budget | Y3: EBITDA_Variance_vs_Budget_pct | Z3: Units_Variance_vs_Budget_pct
A4: 45292 | B4: 2024 | C4: 1 | D4: Jan | E4: Chile | F4: Actual | G4: 11497.14 | H4: 4.3 | I4: 49437.702 | J4: 20579.881 | K4: 28857.821 | L4: 58.372093 | M4: 20833.333 | N4: 8024.4881 | O4: 16.231515 | P4: 14038 | Q4: 97218.79 | R4: 6925.4 | S4: 52700.654 | T4: 8881.777 | U4: 11957.04
A5: 45323 | B5: 2024 | C5: 2 | D5: Feb | E5: Chile | F5: Actual | G5: 13413.33 | H5: 4.3 | I5: 57677.319 | J5: 24009.861 | K5: 33667.458 | L5: 58.372093 | M5: 20833.333 | N5: 12834.125 | O5: 22.251598 | P5: 14038 | Q5: 97218.79 | R5: 6925.4 | S5: 61484.096 | T5: 13973.184 | U5: 13949.88
A6: 45352 | B6: 2024 | C6: 3 | D6: Mar | E6: Chile | F6: Actual | G6: 17245.71 | H6: 4.3 | I6: 74156.553 | J6: 30869.821 | K6: 43286.732 | L6: 58.372093 | M6: 20833.333 | N6: 22453.399 | O6: 30.278374 | P6: 14038 | Q6: 97218.79 | R6: 6925.4 | S6: 79050.981 | T6: 24155.999 | U6: 17935.56
A7: 45383 | B7: 2024 | C7: 4 | D7: Apr | E7: Chile | F7: Actual | G7: 21078.09 | H7: 4.3 | I7: 90635.787 | J7: 37729.781 | K7: 52906.006 | L7: 58.372093 | M7: 20833.333 | N7: 32072.673 | O7: 35.386323 | P7: 14038 | Q7: 97218.79 | R7: 6925.4 | S7: 96617.865 | T7: 34338.813 | U7: 21921.24
A8: 45413 | B8: 2024 | C8: 5 | D8: May | E8: Chile | F8: Actual | G8: 22994.28 | H8: 4.3 | I8: 98875.404 | J8: 41159.761 | K8: 57715.643 | L8: 58.372093 | M8: 20833.333 | N8: 36882.309 | O8: 37.301804 | P8: 14038 | Q8: 97218.79 | R8: 6925.4 | S8: 105401.31 | T8: 39430.221 | U8: 23914.08
A9: 45444 | B9: 2024 | C9: 6 | D9: Jun | E9: Chile | F9: Actual | G9: 21078.09 | H9: 4.3 | I9: 90635.787 | J9: 37729.781 | K9: 52906.006 | L9: 58.372093 | M9: 20833.333 | N9: 32072.673 | O9: 35.386323 | P9: 14038 | Q9: 97218.79 | R9: 6925.4 | S9: 96617.865 | T9: 34338.813 | U9: 21921.24
A10: 45474 | B10: 2024 | C10: 7 | D10: Jul | E10: Chile | F10: Actual | G10: 17245.71 | H10: 4.3 | I10: 74156.553 | J10: 30869.821 | K10: 43286.732 | L10: 58.372093 | M10: 20833.333 | N10: 22453.399 | O10: 30.278374 | P10: 14038 | Q10: 97218.79 | R10: 6925.4 | S10: 79050.981 | T10: 24155.999 | U10: 17935.56
A11: 45505 | B11: 2024 | C11: 8 | D11: Aug | E11: Chile | F11: Actual | G11: 15329.52 | H11: 4.3 | I11: 65916.936 | J11: 27439.841 | K11: 38477.095 | L11: 58.372093 | M11: 20833.333 | N11: 17643.762 | O11: 26.76666 | P11: 14038 | Q11: 97218.79 | R11: 6925.4 | S11: 70267.538 | T11: 19064.592 | U11: 15942.72
A12: 45536 | B12: 2024 | C12: 9 | D12: Sep | E12: Chile | F12: Actual | G12: 13413.33 | H12: 4.3 | I12: 57677.319 | J12: 24009.861 | K12: 33667.458 | L12: 58.372093 | M12: 20833.333 | N12: 12834.125 | O12: 22.251598 | P12: 14038 | Q12: 97218.79 | R12: 6925.4 | S12: 61484.096 | T12: 13973.184 | U12: 13949.88
A13: 45566 | B13: 2024 | C13: 10 | D13: Oct | E13: Chile | F13: Actual | G13: 13413.33 | H13: 4.3 | I13: 57677.319 | J13: 24009.861 | K13: 33667.458 | L13: 58.372093 | M13: 20833.333 | N13: 12834.125 | O13: 22.251598 | P13: 14038 | Q13: 97218.79 | R13: 6925.4 | S13: 61484.096 | T13: 13973.184 | U13: 13949.88
A14: 45597 | B14: 2024 | C14: 11 | D14: Nov | E14: Chile | F14: Actual | G14: 13413.33 | H14: 4.3 | I14: 57677.319 | J14: 24009.861 | K14: 33667.458 | L14: 58.372093 | M14: 20833.333 | N14: 12834.125 | O14: 22.251598 | P14: 14038 | Q14: 97218.79 | R14: 6925.4 | S14: 61484.096 | T14: 13973.184 | U14: 13949.88
A15: 45627 | B15: 2024 | C15: 12 | D15: Dec | E15: Chile | F15: Actual | G15: 11497.14 | H15: 4.3 | I15: 49437.702 | J15: 20579.881 | K15: 28857.821 | L15: 58.372093 | M15: 20833.333 | N15: 8024.4881 | O15: 16.231515 | P15: 14038 | Q15: 97218.79 | R15: 6925.4 | S15: 52700.654 | T15: 8881.777 | U15: 11957.04
... A99: 45992 | B99: 2025 | C99: 12 | D99: Dec | E99: Spain | F99: Budget | G99: 7116.06 | H99: 4.66375 | I99: 33187.525 | J99: 13625.476 | K99: 19562.049 | L99: 58.943983 | M99: 13866.667 | N99: 5695.3823 | O99: 17.161214 | P99: 5180 | Q99: 60950 | R99: 11766.4 | S99: 33187.525 | T99: 5695.3823 | U99: 7116.06
A100: 45658 | B100: 2025 | C100: 1 | D100: Jan | E100: Chile | F100: Forecast | G100: 11239.62 | H100: 4.363425 | I100: 49043.239 | J100: 20823.082 | K100: 28220.157 | L100: 57.541381 | M100: 21666.667 | N100: 6553.4902 | O100: 13.362678 | P100: 14038 | Q100: 97218.79 | R100: 6925.4 | S100: 52700.654 | T100: 8881.777 | U100: 11957.04 | V100: -3657.4149 | W100: -6.9399801 | X100: -2328.2867 | Y100: -26.2142 | Z100: -5.9999799
A101: 45689 | B101: 2025 | C101: 2 | D101: Feb | E101: Chile | F101: Forecast | G101: 13112.89 | H101: 4.363425 | I101: 57217.112 | J101: 24293.596 | K101: 32923.516 | L101: 57.541381 | M101: 21666.667 | N101: 11256.85 | O101: 19.673922 | P101: 14038 | Q101: 97218.79 | R101: 6925.4 | S101: 61484.096 | T101: 13973.184 | U101: 13949.88 | V101: -4266.9841 | W101: -6.9399801 | X101: -2716.3345 | Y101: -19.439624 | Z101: -5.9999799
A102: 45717 | B102: 2025 | C102: 3 | D102: Mar | E102: Chile | F102: Forecast | G102: 16859.43 | H102: 4.363425 | I102: 73564.858 | J102: 31234.623 | K102: 42330.235 | L102: 57.541381 | M102: 21666.667 | N102: 20663.569 | O102: 28.088912 | P102: 14038 | Q102: 97218.79 | R102: 6925.4 | S102: 79050.981 | T102: 24155.999 | U102: 17935.56 | V102: -5486.1224 | W102: -6.9399801 | X102: -3492.4301 | Y102: -14.457817 | Z102: -5.9999799
A103: 45748 | B103: 2025 | C103: 4 | D103: Apr | E103: Chile | F103: Forecast | G103: 20605.97 | H103: 4.363425 | I103: 89912.605 | J103: 38175.65 | K103: 51736.954 | L103: 57.541381 | M103: 21666.667 | N103: 30070.288 | O103: 33.443907 | P103: 14038 | Q103: 97218.79 | R103: 6925.4 | S103: 96617.865 | T103: 34338.813 | U103: 21921.24 | V103: -6705.2607 | W103: -6.9399801 | X103: -4268.5257 | Y103: -12.430615 | Z103: -5.9999799
A104: 45778 | B104: 2025 | C104: 5 | D104: May | E104: Chile | F104: Forecast | G104: 22479.24 | H104: 4.363425 | I104: 98086.478 | J104: 41646.164 | K104: 56440.314 | L104: 57.541381 | M104: 21666.667 | N104: 34773.647 | O104: 35.45203 | P104: 14038 | Q104: 97218.79 | R104: 6925.4 | S104: 105401.31 | T104: 39430.221 | U104: 23914.08 | V104: -7314.8298 | W104: -6.9399801 | X104: -4656.5735 | Y104: -11.809656 | Z104: -5.9999799
A105: 45809 | B105: 2025 | C105: 6 | D105: Jun | E105: Chile | F105: Forecast | G105: 20605.97 | H105: 4.363425 | I105: 89912.605 | J105: 38175.65 | K105: 51736.954 | L105: 57.541381 | M105: 21666.667 | N105: 30070.288 | O105: 33.443907 | P105: 14038 | Q105: 97218.79 | R105: 6925.4 | S105: 96617.865 | T105: 34338.813 | U105: 21921.24 | V105: -6705.2607 | W105: -6.9399801 | X105: -4268.5257 | Y105: -12.430615 | Z105: -5.9999799
A106: 45839 | B106: 2025 | C106: 7 | D106: Jul | E106: Chile | F106: Forecast | G106: 16859.43 | H106: 4.363425 | I106: 73564.858 | J106: 31234.623 | K106: 42330.235 | L106: 57.541381 | M106: 21666.667 | N106: 20663.569 | O106: 28.088912 | P106: 14038 | Q106: 97218.79 | R106: 6925.4 | S106: 79050.981 | T106: 24155.999 | U106: 17935.56 | V106: -5486.1224 | W106: -6.9399801 | X106: -3492.4301 | Y106: -14.457817 | Z106: -5.9999799
A107: 45870 | B107: 2025 | C107: 8 | D107: Aug | E107: Chile | F107: Forecast | G107: 14986.16 | H107: 4.363425 | I107: 65390.985 | J107: 27764.109 | K107: 37626.876 | L107: 57.541381 | M107: 21666.667 | N107: 15960.209 | O107: 24.407354 | P107: 14038 | Q107: 97218.79 | R107: 6925.4 | S107: 70267.538 | T107: 19064.592 | U107: 15942.72 | V107: -4876.5532 | W107: -6.9399801 | X107: -3104.3823 | Y107: -16.283498 | Z107: -5.9999799
A108: 45901 | B108: 2025 | C108: 9 | D108: Sep | E108: Chile | F108: Forecast | G108: 13112.89 | H108: 4.363425 | I108: 57217.112 | J108: 24293.596 | K108: 32923.516 | L108: 57.541381 | M108: 21666.667 | N108: 11256.85 | O108: 19.673922 | P108: 14038 | Q108: 97218.79 | R108: 6925.4 | S108: 61484.096 | T108: 13973.184 | U108: 13949.88 | V108: -4266.9841 | W108: -6.9399801 | X108: -2716.3345 | Y108: -19.439624 | Z108: -5.9999799
A109: 45931 | B109: 2025 | C109: 10 | D109: Oct | E109: Chile | F109: Forecast | G109: 13112.89 | H109: 4.363425 | I109: 57217.112 | J109: 24293.596 | K109: 32923.516 | L109: 57.541381 | M109: 21666.667 | N109: 11256.85 | O109: 19.673922 | P109: 14038 | Q109: 97218.79 | R109: 6925.4 | S109: 61484.096 | T109: 13973.184 | U109: 13949.88 | V109: -4266.9841 | W109: -6.9399801 | X109: -2716.3345 | Y109: -19.439624 | Z109: -5.9999799
A110: 45962 | B110: 2025 | C110: 11 | D110: Nov | E110: Chile | F110: Forecast | G110: 13112.89 | H110: 4.363425 | I110: 57217.112 | J110: 24293.596 | K110: 32923.516 | L110: 57.541381 | M110: 21666.667 | N110: 11256.85 | O110: 19.673922 | P110: 14038 | Q110: 97218.79 | R110: 6925.4 | S110: 61484.096 | T110: 13973.184 | U110: 13949.88 | V110: -4266.9841 | W110: -6.9399801 | X110: -2716.3345 | Y110: -19.439624 | Z110: -5.9999799
A111: 45992 | B111: 2025 | C111: 12 | D111: Dec | E111: Chile | F111: Forecast | G111: 11239.62 | H111: 4.363425 | I111: 49043.239 | J111: 20823.082 | K111: 28220.157 | L111: 57.541381 | M111: 21666.667 | N111: 6553.4902 | O111: 13.362678 | P111: 14038 | Q111: 97218.79 | R111: 6925.4 | S111: 52700.654 | T111: 8881.777 | U111: 11957.04 | V111: -3657.4149 | W111: -6.9399801 | X111: -2328.2867 | Y111: -26.2142 | Z111: -5.9999799
... A147: 45992 | B147: 2025 | C147: 12 | D147: Dec | E147: Spain | F147: Forecast | G147: 6902.58 | H147: 4.6404312 | I147: 32030.948 | J147: 13216.715 | K147: 18814.233 | L147: 58.737671 | M147: 13866.667 | N147: 4947.5662 | O147: 15.446206 | P147: 5180 | Q147: 60950 | R147: 11766.4 | S147: 33187.525 | T147: 5695.3823 | U147: 7116.06 | V147: -1156.5769 | W147: -3.4849748 | X147: -747.81606 | Y147: -13.130217 | Z147: -2.9999747

Sheet Raw_CAPEX
A1: Synthetic CAPEX scenarios for portfolio demonstration. These figures do not represent Fall Creek or any other company.
A3: Scenario | B3: Initial_Investment | C3: Discount_Rate_pct | D3: NPV | E3: IRR_pct | F3: Payback_Years
A4: Downside | B4: 850000 | C4: 10 | D4: -241346.25 | E4: -0.060875331
A5: Base | B5: 850000 | C5: 10 | D5: 218046.07 | E5: 18.030556 | F5: 3.5613413
A6: Upside | B6: 850000 | C6: 10 | D6: 612720.65 | E6: 31.037742 | F6: 2.7932139
A10: Scenario | B10: Year | C10: Units | D10: Price_per_Plant | E10: Variable_Cost_per_Plant | F10: Incremental_Revenue | G10: Incremental_Variable_Cost | H10: Incremental_Fixed_OPEX | I10: Terminal_Value | J10: Net_Cash_Flow
A11: Downside | B11: 0 | C11: 0 | D11: 0 | E11: 0 | F11: 0 | G11: 0 | H11: 0 | I11: 0 | J11: -850000
A12: Downside | B12: 1 | C12: 75000 | D12: 4.1225 | E12: 1.89 | F12: 309187.5 | G12: 141750 | H12: 80000 | I12: 0 | J12: 87437.5
A13: Downside | B13: 2 | C13: 90000 | D13: 4.20495 | E13: 1.9467 | F13: 378445.5 | G13: 175203 | H13: 82400 | I13: 0 | J13: 120842.5
A14: Downside | B14: 3 | C14: 105000 | D14: 4.289049 | E14: 2.005101 | F14: 450350.15 | G14: 210535.61 | H14: 84872 | I14: 0 | J14: 154942.54
A15: Downside | B15: 4 | C15: 120000 | D15: 4.37483 | E15: 2.065254 | F15: 524979.6 | G15: 247830.48 | H15: 87418.16 | I15: 0 | J15: 189730.95
A16: Downside | B16: 5 | C16: 135000 | D16: 4.4623266 | E16: 2.1272117 | F16: 602414.09 | G16: 287173.57 | H16: 90040.705 | I16: 70000 | J16: 295199.81
A17: Base | B17: 0 | C17: 0 | D17: 0 | E17: 0 | F17: 0 | G17: 0 | H17: 0 | I17: 0 | J17: -850000
A18: Base | B18: 1 | C18: 100000 | D18: 4.25 | E18: 1.75 | F18: 425000 | G18: 175000 | H18: 80000 | I18: 0 | J18: 170000
A19: Base | B19: 2 | C19: 120000 | D19: 4.335 | E19: 1.8025 | F19: 520200 | G19: 216300 | H19: 82400 | I19: 0 | J19: 221500
A20: Base | B20: 3 | C20: 140000 | D20: 4.4217 | E20: 1.856575 | F20: 619038 | G20: 259920.5 | H20: 84872 | I20: 0 | J20: 274245.5
A21: Base | B21: 4 | C21: 160000 | D21: 4.510134 | E21: 1.9122723 | F21: 721621.44 | G21: 305963.56 | H21: 87418.16 | I21: 0 | J21: 328239.72
A22: Base | B22: 5 | C22: 180000 | D22: 4.6003367 | E22: 1.9696404 | F22: 828060.6 | G22: 354535.28 | H22: 90040.705 | I22: 100000 | J22: 483484.62
... A28: Upside | B28: 5 | C28: 216000 | D28: 4.7383468 | E28: 1.9105512 | F28: 1023482.9 | G28: 412679.06 | H28: 90040.705 | I28: 120000 | J28: 640763.14
